nhonga_api/__init__.py
nhonga_api/client.py
nhonga_api/examples.py
nhonga_api/types.py
nhonga_api-1.0.0.dist-info/METADATA
nhonga_api-1.0.0.dist-info/WHEEL
nhonga_api-1.0.0.dist-info/top_level.txt
nhonga_api-1.0.0.dist-info/RECORD
